pie_manager/__init__.py
pie_manager/__main__.py
pie_manager/cli.py
pie_manager-1.0.7.1.dist-info/LICENSE
pie_manager-1.0.7.1.dist-info/METADATA
pie_manager-1.0.7.1.dist-info/WHEEL
pie_manager-1.0.7.1.dist-info/entry_points.txt
pie_manager-1.0.7.1.dist-info/top_level.txt
pie_manager-1.0.7.1.dist-info/RECORD
