Metadata-Version: 2.1
Name: pie-manager
Version: 1.0.7.1
Summary: A very loose and easy to use project manager
Home-page: https://github.com/skandabhairava/Pie-manager
Author: Terroid
Author-email: skandabhairava@gmail.com
Project-URL: Bug Tracker, https://github.com/skandabhairava/Pie-manager/issues
Classifier: Programming Language :: Python :: 3
Classifier: License :: OSI Approved :: MIT License
Classifier: Operating System :: OS Independent
Requires-Python: >=3.8
License-File: LICENSE
